gcm_common/__init__.py
gcm_common/exception.py
gcm_common/logger.py
gcm_common/logging.yaml
gcm_common/mplog.py
gcm_common/response.py
gcm_common/updater.py
gcm_common-0.2.0.dist-info/METADATA
gcm_common-0.2.0.dist-info/WHEEL
gcm_common-0.2.0.dist-info/RECORD
